setup.py
sunnyjudge/__init__.py
sunnyjudge/main.py
sunnyjudge/test.py
sunnyjudge.egg-info/PKG-INFO
sunnyjudge.egg-info/SOURCES.txt
sunnyjudge.egg-info/dependency_links.txt
sunnyjudge.egg-info/not-zip-safe
sunnyjudge.egg-info/requires.txt
sunnyjudge.egg-info/top_level.txt