Metadata-Version: 1.0
Name: sunnyjudge
Version: 0.1
Summary: 開箱即用的司法陽光網判決
Home-page: https://github.com/yudazilian/SunnyJudge
Author: yudazilian
Author-email: davisfreeman1015@gmail.com
License: MIT
Platform: UNKNOWN
